setup.py
constant_listener/__init__.py
constant_listener/constant_listener.py
constant_listener/g2p.py
constant_listener/pyspeech.py
constant_listener/pyspeechTest.py
constant_listener/vocabcompiler.py
constant_listener.egg-info/PKG-INFO
constant_listener.egg-info/SOURCES.txt
constant_listener.egg-info/dependency_links.txt
constant_listener.egg-info/requires.txt
constant_listener.egg-info/top_level.txt