Metadata-Version: 1.0
Name: constant-listener
Version: 0.0.2
Summary: STT engine that listens in the background
Home-page: https://github.com/MattWis/constant_listener.git
Author: Matt Wismer
Author-email: mattwis86@gmail.com
License: MIT
Platform: UNKNOWN
